microdrop_client/__init__.py
microdrop_client-0.0.1.dist-info/LICENSE
microdrop_client-0.0.1.dist-info/WHEEL
microdrop_client-0.0.1.dist-info/METADATA
microdrop_client-0.0.1.dist-info/RECORD
